bettergit/__init__.py
bettergit/config.py
bettergit/cli/__init__.py
bettergit/cli/main.py
bettergit/cli/utils.py
bettergit/cli/commands/add.py
bettergit/cli/commands/branch.py
bettergit/cli/commands/branch_info.py
bettergit/cli/commands/commit.py
bettergit/cli/commands/create_branch.py
bettergit/cli/commands/create_tag.py
bettergit/cli/commands/delete_branch.py
bettergit/cli/commands/delete_tag.py
bettergit/cli/commands/push.py
bettergit/cli/commands/suggest.py
bettergit/cli/commands/switch.py
bettergit/cli/commands/tag.py
bettergit/core/__init__.py
bettergit/core/branchmeta.py
bettergit/core/classify.py
bettergit/core/gitio.py
bettergit/core/template.py
bettergit/llm/__init__.py
bettergit/llm/client.py
bettergit/llm/pipeline.py
bettergit/llm/prompts.py
bettergit-2.1.3.dist-info/licenses/LICENSE
bettergit-2.1.3.dist-info/METADATA
bettergit-2.1.3.dist-info/WHEEL
bettergit-2.1.3.dist-info/entry_points.txt
bettergit-2.1.3.dist-info/top_level.txt
bettergit-2.1.3.dist-info/RECORD
