Metadata-Version: 2.4
Name: bettergit
Version: 2.1.3
Summary: BetterGit is a conversational CLI wrapper for Git that encourages Conventional Commits.
Requires-Python: >=3.10
License-File: LICENSE
Requires-Dist: typer>=0.9
Requires-Dist: rich>=13.0
Requires-Dist: typing-extensions>=4.6; python_version < "3.11"
Dynamic: license-file
